README.rst
setup.py
shackles.py
shackles.egg-info/PKG-INFO
shackles.egg-info/SOURCES.txt
shackles.egg-info/dependency_links.txt
shackles.egg-info/top_level.txt
tests/__init__.py
tests/test_shackles.py