Metadata-Version: 1.1
Name: shackles
Version: 0.1.1
Summary: Recursive attribute tools.
Home-page: https://github.com/barberj/shackles
Author: Justin Barber
Author-email: barber.justin@gmail.com
License: MIT
Platform: UNKNOWN
Classifier: License :: OSI Approved :: MIT License
Classifier: Development Status :: 5 - Production/Stable
Classifier: Intended Audience :: Developers
Classifier: Programming Language :: Python
Classifier: Topic :: Utilities
Classifier: Programming Language :: Python :: 2.6
Classifier: Programming Language :: Python :: 2.7
Classifier: Programming Language :: Python :: 3.2
